django_factory_all/__init__.py
django_factory_all/model_factory.py
django_factory_all-0.1.0.dist-info/METADATA
django_factory_all-0.1.0.dist-info/WHEEL
django_factory_all-0.1.0.dist-info/top_level.txt
django_factory_all-0.1.0.dist-info/RECORD
