Metadata-Version: 2.4
Name: django_factory_all
Version: 0.1.0
Summary: Un package Django pour générer automatiquement des instances de modèles.
Author-email: Cédric herve Youan <hervecedricyouan@gmail.com>
License: MIT
Project-URL: Homepage, https://github.com/alzeph/django_factory_all
Requires-Python: >=3.8
Requires-Dist: Django==6.0.1
Requires-Dist: Faker==40.1.2
Requires-Dist: sqlparse==0.5.5
Requires-Dist: tzdata==2025.3
